to7m_qt/__init__.py
to7m_qt/bases.py
to7m_qt/prevent_del.py
to7m_qt/widgets/__init__.py
to7m_qt/widgets/button_group.py
to7m_qt/widgets/core_application.py
to7m_qt/widgets/file_dialog.py
to7m_qt-0.0.0.dist-info/LICENSE.TXT
to7m_qt-0.0.0.dist-info/METADATA
to7m_qt-0.0.0.dist-info/WHEEL
to7m_qt-0.0.0.dist-info/top_level.txt
to7m_qt-0.0.0.dist-info/RECORD
