Metadata-Version: 2.1
Name: to7m-qt
Version: 0.0.0
Summary: Wrappings for PySide.
Home-page: https://gitlab.com/to7m/to7m_qt.git
Author: to7m
Author-email: mail@to7m.lol
License: UNKNOWN
Platform: UNKNOWN
Classifier: Programming Language :: Python :: 3
Classifier: License :: OSI Approved :: GNU Affero General Public License v3
Classifier: Operating System :: POSIX :: Linux
Requires-Python: >=3.10
License-File: LICENSE.TXT
Requires-Dist: PySide6 (<7,>=6.0.0)
Requires-Dist: to7m-context (<1,>=0.0.0)
